[{
    "first_name": "John",
    "last_name": "Doe",
    "email": "jdough@gmail.com",
    "password": "doughboy123",
    "skills":"HTML, CSS, Javascript",
    "wage_low": 25,
    "wage_high": 35
},
{
    "first_name": "Tucker",
    "last_name": "Bolt",
    "email": "Tbolt@yahoo.com",
    "password": "Bolt123",
    "skills":"HTML, CSS",
    "wage_low": 20,
    "wage_high": 30
},
{
    "first_name": "Isaiah",
    "last_name": "Keller",
    "email": "Ikeller@gmail.com",
    "password": "keller123",
    "skills":"HTML, CSS, Javascript, MySQL, React",
    "wage_low": 35,
    "wage_high": 45
},
{ 
    "first_name": "Anthony",
    "last_name": "White",
    "email": "Ant@aol.com",
    "password": "Antman9",
    "skills":"Python, Java, MySQL",
    "wage_low": 25,
    "wage_high": 35
},
{
    "first_name": "James",
    "last_name": "Collins",
    "email": "Jcollins@gmail.com",
    "password": "Collins567",
    "skills":"HTML, CSS, Javascript",
    "wage_low": 25,
    "wage_high": 30
},
{
    "first_name": "Chris",
    "last_name": "Knowseverything",
    "email": "knowitall@gmail.com",
    "password": "chris123",
    "skills":"HTML, CSS, Javascript, TypeScript, React, Python, Java, NodeJS, MySql, PHP, C++",
    "wage_low": 25,
    "wage_high": 30
},
{
    "first_name": "Jamie",
    "last_name": "Capadocia",
    "email": "bighatguy@gmail.com",
    "password": "jamie123",
    "skills":"HTML, CSS, Javascript,NodeJS, MySql,",
    "wage_low": 25,
    "wage_high": 30
}]
